ilabs.client-1.3.0-nspkg.pth
ilabs/client/__init__.py
ilabs/client/get_secret.py
ilabs/client/ilabs_api.py
ilabs/client/ilabs_bulk_predict.py
ilabs/client/ilabs_datavault_api.py
ilabs/client/ilabs_datavault_bulk_predict.py
ilabs/client/ilabs_datavault_predictor.py
ilabs/client/ilabs_predictor.py
ilabs/client/ilabs_tagger.py
ilabs/client/send_request.py
ilabs.client-1.3.0.dist-info/LICENSE
ilabs.client-1.3.0.dist-info/METADATA
ilabs.client-1.3.0.dist-info/WHEEL
ilabs.client-1.3.0.dist-info/entry_points.txt
ilabs.client-1.3.0.dist-info/namespace_packages.txt
ilabs.client-1.3.0.dist-info/top_level.txt
ilabs.client-1.3.0.dist-info/RECORD
