Metadata-Version: 2.1
Name: ilabs.client
Version: 1.3.0
Summary: Python client to connect to api.innodatalabs.com
Home-page: https://github.com/innodatalabs/ilabs.client
Author: Mike Kroutikov
Author-email: mkroutikov@innodata.com
License: MIT
Keywords: innodatalabs api rest
Platform: UNKNOWN
Classifier: Development Status :: 4 - Beta
Classifier: Intended Audience :: Developers
Classifier: License :: OSI Approved :: MIT License
Classifier: Programming Language :: Python :: 3
Classifier: Programming Language :: Python :: 3.3
Classifier: Programming Language :: Python :: 3.4
Classifier: Programming Language :: Python :: 3.5
Classifier: Programming Language :: Python :: 3.6
Classifier: Programming Language :: Python :: 3.7
Classifier: Programming Language :: Python :: Implementation :: CPython
Classifier: Programming Language :: Python :: Implementation :: PyPy
Classifier: Topic :: Software Development :: Libraries :: Python Modules
Requires-Dist: lxml (>=4.1.0)
